reflex_api/__init__.py
reflex_api/app.py
reflex_api/wsgi.py
Reflex_API-0.1a1.dist-info/LICENSE
Reflex_API-0.1a1.dist-info/METADATA
Reflex_API-0.1a1.dist-info/WHEEL
Reflex_API-0.1a1.dist-info/top_level.txt
Reflex_API-0.1a1.dist-info/RECORD
